s4l_dti/__init__.py
s4l_dti/cli.py
s4l_dti/data.py
s4l_dti/denoise.py
s4l_dti/imshow.py
s4l_dti/py.typed
s4l_dti/reconstruct.py
s4l_dti/register.py
s4l_dti-1.0.0.dist-info/LICENSE
s4l_dti-1.0.0.dist-info/METADATA
s4l_dti-1.0.0.dist-info/WHEEL
s4l_dti-1.0.0.dist-info/entry_points.txt
s4l_dti-1.0.0.dist-info/top_level.txt
s4l_dti-1.0.0.dist-info/RECORD
