Metadata-Version: 2.1
Name: s4l-dti
Version: 1.0.0
Summary: Help pre-processing of DTI for use in Sim4Life
Home-page: https://github.com/dyollb/s4l-dti
License: MIT License
Project-URL: Bug Tracker, https://github.com/dyollb/s4l-dti/issues
Project-URL: Source Code, https://github.com/dyollb/s4l-dti
License-File: LICENSE
Requires-Dist: dipy
Requires-Dist: numpy <2.0
Requires-Dist: SimpleITK
Provides-Extra: cli
Requires-Dist: typer-slim ; extra == 'cli'
Provides-Extra: dev
Requires-Dist: build ; extra == 'dev'
Requires-Dist: mypy ; extra == 'dev'
Requires-Dist: pre-commit ; extra == 'dev'
Requires-Dist: pytest ; extra == 'dev'
Requires-Dist: testbook ; extra == 'dev'
Provides-Extra: nb
Requires-Dist: ipykernel ; extra == 'nb'
Requires-Dist: matplotlib ; extra == 'nb'
